paragraphe/__init__.py
paragraphe-0.0.1.dist-info/METADATA
paragraphe-0.0.1.dist-info/RECORD
paragraphe-0.0.1.dist-info/WHEEL
paragraphe-0.0.1.dist-info/top_level.txt
