Metadata-Version: 2.1
Name: paragraphe
Version: 0.0.1
Summary: Paragraphe package
Home-page: UNKNOWN
Author: alaaelyassir
Author-email: alaa.elyassir@gmail.com
License: UNKNOWN
Platform: UNKNOWN
Classifier: Programming Language :: Python :: 3
Classifier: License :: OSI Approved :: MIT License
Classifier: Operating System :: OS Independent
